pybookoo/__init__.py
pybookoo/bookooscale.py
pybookoo/const.py
pybookoo/decode.py
pybookoo/exceptions.py
pybookoo/helpers.py
pybookoo/py.typed
pybookoo-0.4.2.dist-info/licenses/LICENSE
pybookoo-0.4.2.dist-info/METADATA
pybookoo-0.4.2.dist-info/WHEEL
pybookoo-0.4.2.dist-info/top_level.txt
pybookoo-0.4.2.dist-info/RECORD
