Metadata-Version: 2.4
Name: pybookoo
Version: 0.4.2
Summary: Async Python library for Bookoo BLE scales
Author-email: taliexo <mail@taliexo.com>
Maintainer-email: taliexo <mail@taliexo.com>
License-Expression: MIT
Project-URL: Homepage, https://github.com/taliexo/pybookoo
Project-URL: Repository, https://github.com/taliexo/pybookoo
Project-URL: Documentation, https://github.com/taliexo/pybookoo
Keywords: Bookoo,Bluetooth,api,async,client
Classifier: Development Status :: 4 - Beta
Classifier: Framework :: AsyncIO
Classifier: Intended Audience :: Developers
Classifier: Natural Language :: English
Classifier: Programming Language :: Python
Classifier: Programming Language :: Python :: 3.13
Requires-Python: >=3.11
License-File: LICENSE
Requires-Dist: bleak>=0.22.0
Provides-Extra: dev
Requires-Dist: covdefaults==2.3.0; extra == "dev"
Requires-Dist: coverage==7.8.2; extra == "dev"
Requires-Dist: syrupy==4.9.1; extra == "dev"
Requires-Dist: pytest==8.4.0; extra == "dev"
Requires-Dist: pytest-asyncio==1.0.0; extra == "dev"
Requires-Dist: pytest-cov==6.1.1; extra == "dev"
Dynamic: license-file
